horaedb_client-2.0.0.dist-info/METADATA
horaedb_client-2.0.0.dist-info/WHEEL
horaedb_client-2.0.0.dist-info/licenses/LICENSE
horaedb_client-2.0.0.dist-info/licenses/NOTICE
horaedb_client.libs/libgcc_s-b5472b99.so.1
horaedb_client/__init__.py
horaedb_client/__init__.pyi
horaedb_client/py.typed
horaedb_client/horaedb_client.abi3.so
horaedb_client-2.0.0.dist-info/RECORD
