Metadata-Version: 2.4
Name: horaedb-client
Version: 2.0.0
Classifier: Programming Language :: Rust
Classifier: Programming Language :: Python :: Implementation :: CPython
Classifier: Programming Language :: Python :: Implementation :: PyPy
Classifier: Operating System :: OS Independent
Classifier: Topic :: Software Development
Classifier: Intended Audience :: Developers
License-File: LICENSE
License-File: NOTICE
Summary: Python client for Apache HoraeDB(incubating), a high-performance, distributed, cloud native time-series database.
Keywords: database,time-series,iot,devops
Author: HoraeDB Authors
License: Apache-2.0
Requires-Python: >=3.7
Project-URL: Documentation, https://github.com/apache/horaedb-client-py
Project-URL: Homepage, https://github.com/apache/horaedb-client-py
Project-URL: Repository, https://github.com/apache/horaedb-client-py
